mcp_djh_order/__init__.py
mcp_djh_order-0.1.0.dist-info/METADATA
mcp_djh_order-0.1.0.dist-info/WHEEL
mcp_djh_order-0.1.0.dist-info/entry_points.txt
mcp_djh_order-0.1.0.dist-info/RECORD
