Metadata-Version: 2.4
Name: mcp-djh-order
Version: 0.1.0
Summary: Add your description here
Author: dartou
Requires-Python: >=3.11
Requires-Dist: mcp[cli]>=1.10.1
Requires-Dist: requests
